horus_deploy/__init__.py
horus_deploy/_config.py
horus_deploy/cli.py
horus_deploy/default_id_ed25519
horus_deploy/default_id_ed25519.pub
horus_deploy/deploys.py
horus_deploy/host.py
horus_deploy/metadata.py
horus_deploy/ssh.py
horus_deploy/utils.py
horus_deploy/builtin_deploy_scripts/__init__.py
horus_deploy/builtin_deploy_scripts/diagnostics.py
horus_deploy/builtin_deploy_scripts/install_package.py
horus_deploy/builtin_deploy_scripts/install_ssh_key.py
horus_deploy/builtin_deploy_scripts/install_webbuilder.py
horus_deploy/builtin_deploy_scripts/mender.py
horus_deploy/builtin_deploy_scripts/mender_commit.py
horus_deploy/builtin_deploy_scripts/reboot.py
horus_deploy/builtin_deploy_scripts/timedate.py
horus_deploy/builtin_deploy_scripts/uname.py
horus_deploy/builtin_deploy_scripts/uninstall_package.py
horus_deploy/operations/__init__.py
horus_deploy/operations/package.py
horus_deploy/operations/system.py
horus_deploy-0.6.5.dist-info/LICENSE
horus_deploy-0.6.5.dist-info/METADATA
horus_deploy-0.6.5.dist-info/WHEEL
horus_deploy-0.6.5.dist-info/entry_points.txt
horus_deploy-0.6.5.dist-info/top_level.txt
horus_deploy-0.6.5.dist-info/RECORD
