Metadata-Version: 2.1
Name: horus-deploy
Version: 0.6.5
Summary: Configuration deployment for Horus devices.
Author: Horus View and Explore B.V.
Author-email: info@horus.nu
License: MIT
Platform: UNKNOWN
Classifier: Intended Audience :: Developers
Classifier: License :: OSI Approved :: MIT License
Classifier: Operating System :: OS Independent
Classifier: Programming Language :: Python :: 3.8
Classifier: Programming Language :: Python :: 3.9
Classifier: Programming Language :: Python :: 3.10
Requires-Python: >=3.8
License-File: LICENSE
Requires-Dist: click
Requires-Dist: pyinfra (==1.7.3)
Requires-Dist: tabulate
Requires-Dist: zeroconf
